schemainspect/__init__.py
schemainspect/command.py
schemainspect/get.py
schemainspect/graphlib/__init__.py
schemainspect/inspected.py
schemainspect/inspector.py
schemainspect/misc.py
schemainspect/pg/__init__.py
schemainspect/pg/obj.py
schemainspect/pg/sql/collations.sql
schemainspect/pg/sql/collations9.sql
schemainspect/pg/sql/comments.sql
schemainspect/pg/sql/constraints.sql
schemainspect/pg/sql/deps.sql
schemainspect/pg/sql/domains.sql
schemainspect/pg/sql/enums.sql
schemainspect/pg/sql/extensions.sql
schemainspect/pg/sql/functions.sql
schemainspect/pg/sql/indexes.sql
schemainspect/pg/sql/privileges.sql
schemainspect/pg/sql/relations.sql
schemainspect/pg/sql/relations9.sql
schemainspect/pg/sql/rlspolicies.sql
schemainspect/pg/sql/schemas.sql
schemainspect/pg/sql/sequences.sql
schemainspect/pg/sql/triggers.sql
schemainspect/pg/sql/types.sql
schemainspect/tableformat.py
schema_inspect_maintained-1.2.0.dist-info/LICENSE
schema_inspect_maintained-1.2.0.dist-info/METADATA
schema_inspect_maintained-1.2.0.dist-info/WHEEL
schema_inspect_maintained-1.2.0.dist-info/entry_points.txt
schema_inspect_maintained-1.2.0.dist-info/RECORD
