Metadata-Version: 2.3
Name: schema-inspect-maintained
Version: 1.2.0
Summary: Schema inspection for PostgreSQL (and possibly others)
License: Unlicense
Author: Robert Lechte
Author-email: robertlechte@gmail.com
Requires-Python: >=3.9,<4
Classifier: License :: OSI Approved
Classifier: Programming Language :: Python :: 3
Classifier: Programming Language :: Python :: 3.9
Classifier: Programming Language :: Python :: 3.10
Classifier: Programming Language :: Python :: 3.11
Classifier: Programming Language :: Python :: 3.12
Classifier: Programming Language :: Python :: 3.13
Requires-Dist: setuptools (>=80.8.0,<81.0.0)
Requires-Dist: sqlalchemy (==1.4.46)
Requires-Dist: sqlbag (>=0.1.1616028516)
Project-URL: Homepage, https://github.com/philipwee/schemainspect
Project-URL: Repository, https://github.com/philipwee/schemainspect
